notevennexus/__init__.py
notevennexus/__main__.py
notevennexus/hdf5.py
notevennexus/io.py
notevennexus/json.py
notevennexus/py.typed
notevennexus/tree.py
notevennexus/validate.py
notevennexus/validators.py
notevennexus-0.4.0.dist-info/LICENSE
notevennexus-0.4.0.dist-info/METADATA
notevennexus-0.4.0.dist-info/WHEEL
notevennexus-0.4.0.dist-info/entry_points.txt
notevennexus-0.4.0.dist-info/top_level.txt
notevennexus-0.4.0.dist-info/RECORD
