Metadata-Version: 2.1
Name: notevennexus
Version: 0.4.0
Summary: Validate NeXus files
Author: Scipp contributors
License: BSD 3-Clause License
Project-URL: Bug Tracker, https://github.com/scipp/notevennexus/issues
Project-URL: Documentation, https://scipp.github.io/notevennexus
Project-URL: Source, https://github.com/scipp/notevennexus
Classifier: Intended Audience :: Science/Research
Classifier: License :: OSI Approved :: BSD License
Classifier: Natural Language :: English
Classifier: Operating System :: OS Independent
Classifier: Programming Language :: Python :: 3
Classifier: Programming Language :: Python :: 3 :: Only
Classifier: Programming Language :: Python :: 3.10
Classifier: Programming Language :: Python :: 3.11
Classifier: Programming Language :: Python :: 3.12
Classifier: Topic :: Scientific/Engineering
Classifier: Typing :: Typed
Requires-Python: >=3.10
License-File: LICENSE
Requires-Dist: h5py
Requires-Dist: platformdirs <4
